insdc_benchmarking_schema/__init__.py
insdc_benchmarking_schema/data/result-schema-v1.1.json
insdc_benchmarking_schema/data/result-schema-v1.2.json
insdc_benchmarking_schema/examples/example_result.json
insdc_benchmarking_schema/models.py
insdc_benchmarking_schema/schema.py
insdc_benchmarking_schema/validator.py
insdc_benchmarking_schema-1.2.0.dist-info/METADATA
insdc_benchmarking_schema-1.2.0.dist-info/WHEEL
insdc_benchmarking_schema-1.2.0.dist-info/licenses/LICENSE
insdc_benchmarking_schema-1.2.0.dist-info/RECORD
